main.py
pychetz-0.1.1.dist-info/licenses/LICENSE
pychetz-0.1.1.dist-info/METADATA
pychetz-0.1.1.dist-info/WHEEL
pychetz-0.1.1.dist-info/entry_points.txt
pychetz-0.1.1.dist-info/top_level.txt
pychetz-0.1.1.dist-info/RECORD
